odoo/addons/account_statement_import_online/README.rst
odoo/addons/account_statement_import_online/__init__.py
odoo/addons/account_statement_import_online/__manifest__.py
odoo/addons/account_statement_import_online/data/account_statement_import_online.xml
odoo/addons/account_statement_import_online/i18n/account_statement_import_online.pot
odoo/addons/account_statement_import_online/i18n/it.po
odoo/addons/account_statement_import_online/i18n/nl.po
odoo/addons/account_statement_import_online/migrations/14.0.1.0.0/pre-migration.py
odoo/addons/account_statement_import_online/migrations/14.0.3.0.0/post-migration.py
odoo/addons/account_statement_import_online/migrations/14.0.3.0.0/pre-migration.py
odoo/addons/account_statement_import_online/models/__init__.py
odoo/addons/account_statement_import_online/models/account_journal.py
odoo/addons/account_statement_import_online/models/online_bank_statement_provider.py
odoo/addons/account_statement_import_online/readme/CONFIGURE.rst
odoo/addons/account_statement_import_online/readme/CONTRIBUTORS.rst
odoo/addons/account_statement_import_online/readme/DESCRIPTION.rst
odoo/addons/account_statement_import_online/readme/USAGE.rst
odoo/addons/account_statement_import_online/security/ir.model.access.csv
odoo/addons/account_statement_import_online/security/online_bank_statement_provider.xml
odoo/addons/account_statement_import_online/static/description/icon.png
odoo/addons/account_statement_import_online/static/description/index.html
odoo/addons/account_statement_import_online/tests/__init__.py
odoo/addons/account_statement_import_online/tests/online_bank_statement_provider_dummy.py
odoo/addons/account_statement_import_online/tests/test_account_journal.py
odoo/addons/account_statement_import_online/tests/test_account_statement_import_online.py
odoo/addons/account_statement_import_online/views/account_journal.xml
odoo/addons/account_statement_import_online/views/actions.xml
odoo14_addon_account_statement_import_online-14.0.4.0.0.dist-info/METADATA
odoo14_addon_account_statement_import_online-14.0.4.0.0.dist-info/WHEEL
odoo14_addon_account_statement_import_online-14.0.4.0.0.dist-info/top_level.txt
odoo14_addon_account_statement_import_online-14.0.4.0.0.dist-info/RECORD
